{
  "^GSPC": {
    "price": 7444.25,
    "change": 43.289999999999964,
    "change_pct": 0.58,
    "prev_close": 7400.96
  },
  "^IXIC": {
    "price": 26402.344,
    "change": 314.1409999999996,
    "change_pct": 1.2,
    "prev_close": 26088.203
  },
  "^DJI": {
    "price": 49693.2,
    "change": -67.36000000000058,
    "change_pct": -0.14,
    "prev_close": 49760.56
  },
  "^FTSE": {
    "price": 10333.39,
    "change": 8.039999999999054,
    "change_pct": 0.08,
    "prev_close": 10325.35
  },
  "^GDAXI": {
    "price": 24390.0,
    "change": 253.1899999999987,
    "change_pct": 1.05,
    "prev_close": 24136.81
  },
  "^FCHI": {
    "price": 8047.92,
    "change": 39.94999999999982,
    "change_pct": 0.5,
    "prev_close": 8007.97
  },
  "^N225": {
    "price": 62654.05,
    "change": -618.0599999999977,
    "change_pct": -0.98,
    "prev_close": 63272.11
  },
  "GC=F": {
    "price": 4706.3,
    "change": -0.3999999999996362,
    "change_pct": -0.01,
    "prev_close": 4706.7
  },
  "SI=F": {
    "price": 87.76,
    "change": -1.6079999999999899,
    "change_pct": -1.8,
    "prev_close": 89.368
  },
  "CL=F": {
    "price": 101.67,
    "change": 0.6500000000000057,
    "change_pct": 0.64,
    "prev_close": 101.02
  },
  "AAPL": {
    "price": 298.87,
    "change": 4.069999999999993,
    "change_pct": 1.38,
    "prev_close": 294.8
  },
  "MSFT": {
    "price": 405.21,
    "change": -2.5600000000000023,
    "change_pct": -0.63,
    "prev_close": 407.77
  },
  "NVDA": {
    "price": 225.83,
    "change": 5.050000000000011,
    "change_pct": 2.29,
    "prev_close": 220.78
  },
  "TSLA": {
    "price": 445.27,
    "change": 11.819999999999993,
    "change_pct": 2.73,
    "prev_close": 433.45
  },
  "GOOGL": {
    "price": 402.62,
    "change": 15.269999999999982,
    "change_pct": 3.94,
    "prev_close": 387.35
  },
  "AMZN": {
    "price": 270.13,
    "change": 4.310000000000002,
    "change_pct": 1.62,
    "prev_close": 265.82
  },
  "SPY": {
    "price": 742.31,
    "change": 4.1299999999999955,
    "change_pct": 0.56,
    "prev_close": 738.18
  },
  "QQQ": {
    "price": 714.71,
    "change": 7.470000000000027,
    "change_pct": 1.06,
    "prev_close": 707.24
  },
  "GLD": {
    "price": 430.5,
    "change": -2.430000000000007,
    "change_pct": -0.56,
    "prev_close": 432.93
  },
  "ARKK": {
    "price": 78.05,
    "change": -0.1599999999999966,
    "change_pct": -0.2,
    "prev_close": 78.21
  },
  "BTC-USD": {
    "price": 79616.34,
    "change": 333.0,
    "change_pct": 0.42,
    "prev_close": 79283.34
  },
  "ETH-USD": {
    "price": 2261.81,
    "change": 4.097400000000107,
    "change_pct": 0.18,
    "prev_close": 2257.7126
  },
  "_updated": "2026-05-14T10:05:10.866983"
}