{
  "^GSPC": {
    "price": 7513.59,
    "change": 69.34000000000015,
    "change_pct": 0.93,
    "prev_close": 7444.25
  },
  "^IXIC": {
    "price": 26693.39,
    "change": 291.04599999999846,
    "change_pct": 1.1,
    "prev_close": 26402.344
  },
  "^DJI": {
    "price": 50156.47,
    "change": 463.2700000000041,
    "change_pct": 0.93,
    "prev_close": 49693.2
  },
  "^FTSE": {
    "price": 10372.93,
    "change": 47.57999999999993,
    "change_pct": 0.46,
    "prev_close": 10325.35
  },
  "^GDAXI": {
    "price": 24456.26,
    "change": 319.4499999999971,
    "change_pct": 1.32,
    "prev_close": 24136.81
  },
  "^FCHI": {
    "price": 8082.27,
    "change": 74.30000000000018,
    "change_pct": 0.93,
    "prev_close": 8007.97
  },
  "^N225": {
    "price": 62654.05,
    "change": -618.0599999999977,
    "change_pct": -0.98,
    "prev_close": 63272.11
  },
  "GC=F": {
    "price": 4692.7,
    "change": -14.0,
    "change_pct": -0.3,
    "prev_close": 4706.7
  },
  "SI=F": {
    "price": 85.47,
    "change": -3.897999999999996,
    "change_pct": -4.36,
    "prev_close": 89.368
  },
  "CL=F": {
    "price": 100.98,
    "change": -0.03999999999999204,
    "change_pct": -0.04,
    "prev_close": 101.02
  },
  "AAPL": {
    "price": 298.87,
    "change": 0.0,
    "change_pct": 0.0,
    "prev_close": 298.87
  },
  "MSFT": {
    "price": 409.042,
    "change": 3.8319999999999936,
    "change_pct": 0.95,
    "prev_close": 405.21
  },
  "NVDA": {
    "price": 235.285,
    "change": 9.454999999999984,
    "change_pct": 4.19,
    "prev_close": 225.83
  },
  "TSLA": {
    "price": 450.525,
    "change": 5.2549999999999955,
    "change_pct": 1.18,
    "prev_close": 445.27
  },
  "GOOGL": {
    "price": 401.09,
    "change": -1.5300000000000296,
    "change_pct": -0.38,
    "prev_close": 402.62
  },
  "AMZN": {
    "price": 268.447,
    "change": -1.6829999999999927,
    "change_pct": -0.62,
    "prev_close": 270.13
  },
  "SPY": {
    "price": 749.2,
    "change": 6.8900000000001,
    "change_pct": 0.93,
    "prev_close": 742.31
  },
  "QQQ": {
    "price": 721.654,
    "change": 6.94399999999996,
    "change_pct": 0.97,
    "prev_close": 714.71
  },
  "GLD": {
    "price": 429.22,
    "change": -1.2799999999999727,
    "change_pct": -0.3,
    "prev_close": 430.5
  },
  "ARKK": {
    "price": 78.92,
    "change": 0.8700000000000045,
    "change_pct": 1.11,
    "prev_close": 78.05
  },
  "BTC-USD": {
    "price": 81491.84,
    "change": 2208.5,
    "change_pct": 2.79,
    "prev_close": 79283.34
  },
  "ETH-USD": {
    "price": 2308.36,
    "change": 50.64740000000029,
    "change_pct": 2.24,
    "prev_close": 2257.7126
  },
  "_updated": "2026-05-14T18:10:11.585935"
}